./.coveragerc
./.gitignore
./LICENSE
./PKG-INFO
./README.rst
./pyproject.toml
./requirements.txt
./script.py
./server.py
./tox.ini
./.github/workflows/ci.yml
./.github/workflows/publish.yml
./app/__init__.py
./app/config.py
./app/extension.py
./app/forms.py
./app/models.py
./app/views.py
./app/libs/__init__.py
./app/static/style.css
./app/templates/home.html
./app/templates/layout.html
./app/templates/login.html
./app/templates/profile.html
./app/templates/register.html
./tests/__init__.py
./tests/conftest.py
./tests/test_app.py
./tests/test_libs.py
./tests/test_models.py
./tests/test_views.py
flask_starter-1.0.0.dist-info/METADATA
flask_starter-1.0.0.dist-info/WHEEL
flask_starter-1.0.0.dist-info/entry_points.txt
flask_starter-1.0.0.dist-info/licenses/LICENSE
flask_starter-1.0.0.dist-info/RECORD
