Metadata-Version: 2.4
Name: flask-starter
Version: 1.0.0
Summary: A cli tool to build basic flask app
Project-URL: Homepage, https://github.com/princekrroshan01/flask-starter
Project-URL: Documentation, https://github.com/princekrroshan01/flask-starter#readme
Project-URL: Repository, https://github.com/princekrroshan01/flask-starter.git
Project-URL: Issues, https://github.com/princekrroshan01/flask-starter/issues
Author-email: Prince Roshan <princekrroshan01@gmail.com>
License: MIT
License-File: LICENSE
Classifier: Development Status :: 4 - Beta
Classifier: Intended Audience :: Developers
Classifier: License :: OSI Approved :: MIT License
Classifier: Operating System :: OS Independent
Classifier: Programming Language :: Python :: 3.8
Classifier: Programming Language :: Python :: 3.9
Classifier: Programming Language :: Python :: 3.10
Classifier: Programming Language :: Python :: 3.11
Classifier: Programming Language :: Python :: 3.12
Classifier: Programming Language :: Python :: 3.13
Requires-Python: >=3.8
Requires-Dist: click>=8.1.7
Requires-Dist: flask-admin>=1.6.1
Requires-Dist: flask-login>=0.6.3
Requires-Dist: flask-sqlalchemy>=3.1.0
Requires-Dist: flask-wtf>=1.2.1
Requires-Dist: flask>=3.0.0
Requires-Dist: gunicorn>=21.2.0
Requires-Dist: httplib2>=0.22.0
Requires-Dist: requests>=2.31.0
Requires-Dist: rich>=13.7.0
Provides-Extra: dev
Requires-Dist: black>=24.1.0; extra == 'dev'
Requires-Dist: flake8>=7.0.0; extra == 'dev'
Requires-Dist: isort>=5.13.0; extra == 'dev'
Requires-Dist: pytest-cov>=4.1.0; extra == 'dev'
Requires-Dist: pytest>=8.0.0; extra == 'dev'
Requires-Dist: tox>=4.11.0; extra == 'dev'
